pyvoro/__init__.py
pyvoro/voroplusplus.cpython-310-x86_64-linux-gnu.so
pyvoro_mmalahe-1.3.4.dist-info/top_level.txt
pyvoro_mmalahe-1.3.4.dist-info/LICENSE.txt
pyvoro_mmalahe-1.3.4.dist-info/WHEEL
pyvoro_mmalahe-1.3.4.dist-info/METADATA
pyvoro_mmalahe-1.3.4.dist-info/LICENSE
pyvoro_mmalahe-1.3.4.dist-info/RECORD
