Metadata-Version: 2.1
Name: pyvoro-mmalahe
Version: 1.3.4
Summary: 2D and 3D Voronoi tessellations: a python entry point for the voro++ library.
Home-page: https://github.com/mmalahe/pyvoro
Author: Joe Jordan
Author-email: joe.jordan@imperial.ac.uk
Keywords: geometry,mathematics,Voronoi
Classifier: Development Status :: 5 - Production/Stable
Classifier: Topic :: Scientific/Engineering :: Mathematics
Classifier: Topic :: Scientific/Engineering :: Physics
Classifier: Intended Audience :: Science/Research
Classifier: Operating System :: POSIX :: Linux
Classifier: Programming Language :: Python :: 3
Classifier: Programming Language :: Python :: 3.11
Classifier: License :: OSI Approved :: BSD License
License-File: LICENSE
License-File: LICENSE.txt
